odoo/addons/base_duration/README.rst
odoo/addons/base_duration/__init__.py
odoo/addons/base_duration/__manifest__.py
odoo/addons/base_duration/i18n/base_duration.pot
odoo/addons/base_duration/models/__init__.py
odoo/addons/base_duration/models/base_duration.py
odoo/addons/base_duration/security/ir.model.access.csv
odoo/addons/base_duration/static/description/icon.png
odoo/addons/base_duration/views/base_duration_views.xml
odoo14_addon_base_duration-14.0.1.1.3.dist-info/METADATA
odoo14_addon_base_duration-14.0.1.1.3.dist-info/WHEEL
odoo14_addon_base_duration-14.0.1.1.3.dist-info/top_level.txt
odoo14_addon_base_duration-14.0.1.1.3.dist-info/RECORD
